LatexLunwenXiezuoJiaochengFix1/README.md
LatexLunwenXiezuoJiaochengFix1/__init__.py
LatexLunwenXiezuoJiaochengFix1/__main__.py
LatexLunwenXiezuoJiaochengFix1/file.epub
LatexLunwenXiezuoJiaochengFix1/index.html
LatexLunwenXiezuoJiaochengFix1/css/__init__.py
LatexLunwenXiezuoJiaochengFix1/css/annotations.css
LatexLunwenXiezuoJiaochengFix1/css/main.css
LatexLunwenXiezuoJiaochengFix1/css/normalize.css
LatexLunwenXiezuoJiaochengFix1/css/popup.css
LatexLunwenXiezuoJiaochengFix1/font/__init__.py
LatexLunwenXiezuoJiaochengFix1/font/fontello.eot
LatexLunwenXiezuoJiaochengFix1/font/fontello.svg
LatexLunwenXiezuoJiaochengFix1/font/fontello.ttf
LatexLunwenXiezuoJiaochengFix1/font/fontello.woff
LatexLunwenXiezuoJiaochengFix1/img/__init__.py
LatexLunwenXiezuoJiaochengFix1/img/annotator-glyph-sprite.png
LatexLunwenXiezuoJiaochengFix1/img/annotator-icon-sprite.png
LatexLunwenXiezuoJiaochengFix1/img/apple-touch-icon.png
LatexLunwenXiezuoJiaochengFix1/img/cancelfullscreen.png
LatexLunwenXiezuoJiaochengFix1/img/close.png
LatexLunwenXiezuoJiaochengFix1/img/fullscreen.png
LatexLunwenXiezuoJiaochengFix1/img/loader.gif
LatexLunwenXiezuoJiaochengFix1/img/menu-icon.png
LatexLunwenXiezuoJiaochengFix1/img/save.png
LatexLunwenXiezuoJiaochengFix1/img/saved.png
LatexLunwenXiezuoJiaochengFix1/img/settings-s.png
LatexLunwenXiezuoJiaochengFix1/img/settings.png
LatexLunwenXiezuoJiaochengFix1/img/star.png
LatexLunwenXiezuoJiaochengFix1/js/__init__.py
LatexLunwenXiezuoJiaochengFix1/js/epub.js
LatexLunwenXiezuoJiaochengFix1/js/epub.min.js
LatexLunwenXiezuoJiaochengFix1/js/epub.min.map
LatexLunwenXiezuoJiaochengFix1/js/hooks.min.js
LatexLunwenXiezuoJiaochengFix1/js/hooks.min.map
LatexLunwenXiezuoJiaochengFix1/js/reader.js
LatexLunwenXiezuoJiaochengFix1/js/reader.js.map
LatexLunwenXiezuoJiaochengFix1/js/reader.min.js
LatexLunwenXiezuoJiaochengFix1/js/reader.min.map
LatexLunwenXiezuoJiaochengFix1/js/hooks/__init__.py
LatexLunwenXiezuoJiaochengFix1/js/hooks/extensions/__init__.py
latex_lunwen_xiezuo_jiaocheng_fix1-2025.3.25.0.dist-info/METADATA
latex_lunwen_xiezuo_jiaocheng_fix1-2025.3.25.0.dist-info/WHEEL
latex_lunwen_xiezuo_jiaocheng_fix1-2025.3.25.0.dist-info/entry_points.txt
latex_lunwen_xiezuo_jiaocheng_fix1-2025.3.25.0.dist-info/top_level.txt
latex_lunwen_xiezuo_jiaocheng_fix1-2025.3.25.0.dist-info/RECORD
